Workbook

Sheet Q2 16
B2: Q3 16 Allocation
B4: Income Profile
H5: Q1 | I5: Q2 | J5: Delta (Q3-Q2)
B6: Statutory Max | D6: Q3 2016 | E6: Vector | F6: Vector Weight | G6: Active USD Long
B7: Equities: | C7: 0.2 | D7: =F7+F8 -> 0.16 | E7: Cell D | F7: 0.1 | H7: 0.15 | I7: 0.13 | J7: =F7-I7 -> -0.03
E8: Exclusif 21 | F8: 0.06 | H8: 0.05 | I8: 0.05 | J8: =F8-I8 -> 0.01
B9: Bonds: | C9: 1 | D9: =F9+F10+F11 -> 0.52 | E9: Cell C | F9: 0.37 | H9: 0.4 | I9: 0.37 | J9: =F9-I9 -> 0
E10: KKR NB C L/S TBC | F10: 0.05 | H10: 0.08 | I10: 0.08 | J10: =F10-I10 -> -0.03
E11: TFC Bonds | F11: 0.1 | H11: 0.07 | I11: 0.1 | J11: =F11-I11 -> 0
B12: Alternatives: | C12: 0.15 | D12: =SUM(F12:F15) -> 0.17 | E12: Gold | F12: 0.07 | H12: 0 | I12: 0 | J12: =F12-I12 -> 0.07
E13: Tactical | F13: 0.07 | H13: 0.07 | I13: 0.07 | J13: =F13-I13 -> 0
E14: Abrax | F14: 0.03 | H14: 0.03 | I14: 0.03 | J14: =F14-I14 -> 0
E15: Syquant | F15: 0 | H15: 0 | I15: 0 | J15: =F15-I15 -> 0
B16: Cash: | C16: 1 | D16: =100%-D12-D9-D7 -> 0.15 | G16: 0.1 | H16: 0.15 | I16: 0.17 | J16: =D16-I16 -> -0.02
B19: Conservative Profile
H20: =H5 -> Q1 | I20: Q2 | J20: =J5 -> Delta (Q3-Q2)
B21: Statutory Max | D21: =D6 -> Q3 2016 | E21: Vector | F21: Vector Weight | G21: Active USD Long
B22: Equities: | C22: 0.3 | D22: =F22+F24+F23 -> 0.28 | E22: Cell D | F22: 0.2 | H22: 0.22 | I22: 0.2 | J22: =F22-I22 -> 0
E23: TFC Small Caps | F23: 0.03 | H23: 0.03 | I23: 0.03 | J23: =F23-I23 -> 0
E24: Exclusif 21 | F24: 0.05 | H24: 0.05 | I24: 0.05 | J24: =F24-I24 -> 0
B25: Bonds: | C25: 0.8 | D25: =F25+F26+F27 -> 0.4 | E25: Cell C | F25: 0.28 | H25: 0.3 | I25: 0.28 | J25: =F25-I25 -> 0
E26: KKR NB C L/S TBC | F26: 0.05 | H26: 0.07 | I26: 0.07 | J26: =F26-I26 -> -0.02
E27: TFC Bonds | F27: 0.07 | H27: 0.05 | I27: 0.07 | J27: =F27-I27 -> 0
B28: Alternatives: | C28: 0.25 | D28: =SUM(F28:F32) -> 0.23 | E28: Gold | F28: 0.05 | H28: 0 | I28: 0 | J28: =F28-I28 -> 0.05
E29: Tactical | F29: 0.09 | H29: 0.03 | I29: 0.07 | J29: =F29-I29 -> 0.02
E30: Abrax | F30: 0.05 | H30: 0.05 | I30: 0.05 | J30: =F30-I30 -> 0
E31: Syquant | F31: 0 | H31: 0 | I31: 0 | J31: =F31-I31 -> 0
E32: Cimco | F32: 0.04 | H32: 0.04 | I32: 0.04 | J32: =F32-I32 -> 0
B33: Cash: | C33: 1 | D33: =100%-D28-D25-D22 -> 0.09 | G33: 0.15 | H33: 0.16 | I33: 0.14 | J33: =D33-I33 -> -0.05
B37: Balanced Profile
H38: =H20 -> Q1 | I38: Q2 | J38: =J20 -> Delta (Q3-Q2)
B39: Statutory Max | D39: =D21 -> Q3 2016 | E39: Vector | F39: Vector Weight | G39: Active USD Long
B40: Equities: | C40: 0.7 | D40: =SUM(F40:F45) -> 0.6 | E40: Cell D | F40: 0.39 | H40: 0.42 | I40: 0.42 | J40: =F40-I40 -> -0.03
E41: Exclusif 21 | F41: 0.06 | H41: 0.06 | I41: 0.06 | J41: =F41-I41 -> 0
E42: TFC Small Caps | F42: 0.04 | H42: 0.03 | I42: 0.04 | J42: =F42-I42 -> 0
E43: Shanti India | F43: 0.04 | H43: 0.03 | I43: 0.04 | J43: =F43-I43 -> 0
E44: Liontrust UK small caps | F44: 0.03 | H44: 0 | I44: 0.03 | J44: =F44-I44 -> 0
E45: Liontrust Asian | F45: 0.04 | H45: 0.03 | I45: 0.04 | J45: =F45-I45 -> 0
B46: Bonds: | C46: 0.5 | D46: =F46+F47 -> 0.15 | E46: Cell C | F46: 0.15 | H46: 0.18 | I46: 0.15 | J46: =F46-I46 -> 0
E47: KKR NB C L/S TBC | F47: 0 | H47: 0.05 | I47: 0 | J47: =F47-I47 -> 0
B48: Alternatives: | C48: 0.3 | D48: =SUM(F48:F52) -> 0.19 | E48: Abrax | F48: 0.05 | H48: 0.06 | I48: 0.05 | J48: =F48-I48 -> 0
E49: Gold | F49: 0.03 | H49: 0 | I49: 0 | J49: =F49-I49 -> 0.03
E50: Tactical | F50: 0.06 | H50: 0.04 | I50: 0.04 | J50: =F50-I50 -> 0.02
E51: Syquant | F51: 0 | H51: 0 | I51: 0 | J51: =F51-I51 -> 0
E52: Cimco | F52: 0.05 | H52: 0.05 | I52: 0.05 | J52: =F52-I52 -> 0
B53: Cash: | C53: 1 | D53: =100%-D48-D46-D40 -> 0.06 | G53: 0.18 | H53: 0.05 | I53: 0.08 | J53: =D53-I53 -> -0.02

Sheet Q4 16
R1: Estimated Downside Risk | V1: Bloomberg Scenario
M2: Return | R2: Average Correction | V2: Risk
B3: Q4 16 Allocation | R3: Correl=1
L4: 12 Mos E® | N4: =SUM(N8:N20) -> 0.03995 | Q4: Risk= | S4: =SUM(S8:S20) -> 0.06075 | Y4: =D8/C8 -> 0.55
B5: Income Profile
H6: Q2 | I6: Q3 | J6: Delta (Q4-Q3)
B7: Statutory Max | D7: Q4 2016 | E7: Vector | F7: Vector Weight | G7: Active USD Long | V7: Worst: | W7: EUR up 10% vs USD
B8: Equities: | C8: 0.2 | D8: =F8+F9 -> 0.11 | E8: Dharma Equities | F8: 0.11 | H8: ='Q2 16'!I7 -> 0.13 | I8: 0.11 | J8: =F8-I8 -> 0 | L8: 0.06 | N8: =L8*F8 -> 0.0066 | Q8: 0.15 | S8: =Q8*F8 -> 0.0165 | V8: Impact: | W8: -0.0407
E9: Exclusif 21 | F9: 0 | H9: ='Q2 16'!I8 -> 0.05 | I9: 0.05 | J9: =F9-I9 -> -0.05 | L9: 0.03 | N9: =L9*F9 -> 0 | Q9: 0.1 | S9: =Q9*F9 -> 0
B10: Bonds: | C10: 1 | D10: =SUM(F10:F13) -> 0.53 | E10: Dharma Bonds | F10: 0.37 | H10: ='Q2 16'!I9 -> 0.37 | I10: 0.37 | J10: =F10-I10 -> 0 | L10: 0.035 | N10: =L10*F10 -> 0.01295 | Q10: 0.055 | S10: =Q10*F10 -> 0.02035 | V10: 2nd Worst: | W10: Lehman Crisis
E11: Muzinich Credit L/S | F11: 0.06 | H11: ='Q2 16'!I10 -> 0.08 | I11: 0 | J11: =F11-I11 -> 0.06 | L11: 0.025 | N11: =L11*F11 -> 0.0015 | Q11: 0.08 | S11: =Q11*F11 -> 0.0048 | W11: -0.029
E12: Arcano Fund | F12: 0.05 | H12: 0 | I12: 0.05 | J12: =F12-I12 -> 0 | L12: 0.04 | N12: =L12*F12 -> 0.002 | Q12: 0.02 | S12: =Q12*F12 -> 0.001
E13: Rendement Euro Plus | F13: 0.05 | H13: ='Q2 16'!I11 -> 0.1 | I13: 0.09 | J13: =F13-I13 -> -0.04 | L13: 0.04 | N13: =L13*F13 -> 0.002 | Q13: 0.1 | S13: =Q13*F13 -> 0.005 | V13: 3rd Worst | W13: Equities down 10%.
B14: Alternatives: | C14: 0.15 | D14: =SUM(F14:F18) -> 0.18 | E14: Gold (buy @1180) | F14: 0.05 | H14: ='Q2 16'!I12 -> 0 | I14: 0 | J14: =F14-I14 -> 0.05 | L14: 0.1 | N14: =L14*F14 -> 0.005 | Q14: 0.1 | S14: =Q14*F14 -> 0.005 | W14: -0.0277
E15: Tactical | F15: 0.07 | H15: ='Q2 16'!I13 -> 0.07 | I15: 0.07 | J15: =F15-I15 -> 0 | L15: 0.02 | N15: =L15*F15 -> 0.0014 | Q15: 0.02 | S15: =Q15*F15 -> 0.0014
E16: Blackwall | F16: 0.03 | H16: 0 | I16: 0 | J16: =F16-I16 -> 0.03 | L16: 0.06 | N16: =L16*F16 -> 0.0018 | Q16: 0.05 | S16: =Q16*F16 -> 0.0015
E17: Abrax | F17: 0.03 | H17: ='Q2 16'!I14 -> 0.03 | I17: 0.03 | J17: =F17-I17 -> 0 | L17: 0.05 | N17: =L17*F17 -> 0.0015 | Q17: 0.04 | S17: =Q17*F17 -> 0.0012
E18: Commodities Fund | F18: 0 | H18: ='Q2 16'!I15 -> 0 | I18: 0.03 | J18: =F18-I18 -> -0.03 | L18: 0.05 | N18: =L18*F18 -> 0 | Q18: 0.04 | S18: =Q18*F18 -> 0
B19: Cash: | C19: 1 | D19: =100%-D14-D10-D8 -> 0.18 | H19: ='Q2 16'!I16 -> 0.17 | I19: ='Q3 16'!I18 -> 0.2 | J19: =D19-I19 -> -0.02 | L19: 0.01 | N19: =I19*L19 -> 0.002 | Q19: 0.15
G20: 0.08 | K20: Active ccy | L20: 0.04 | N20: =L20*G20 -> 0.0032 | Q20: 0.05 | S20: =Q20*G20 -> 0.004
B23: Conservative Profile | L23: 12 Mos E® | N23: =SUM(N26:N39) -> 0.04215 | Q23: =Q4 -> Risk= | S23: =SUM(S26:S40) -> 0.075 | Y23: =D26/C26 -> 0.7
H24: =H6 -> Q2 | I24: =I6 -> Q3 | J24: =J6 -> Delta (Q4-Q3)
B25: Statutory Max | D25: =D7 -> Q4 2016 | E25: Vector | F25: Vector Weight | G25: Active USD Long
B26: Equities: | C26: 0.3 | D26: =F26+F28+F27 -> 0.21 | E26: Dharma Equities | F26: 0.19 | H26: 0.22 | I26: 0.18 | J26: =F26-I26 -> 0.01 | L26: =L8 -> 0.06 | N26: =L26*F26 -> 0.0114 | Q26: =Q8 -> 0.15 | S26: =Q26*F26 -> 0.0285 | V26: Worst: | W26: EUR up 10% vs USD
E27: TFC Small Caps | F27: 0.02 | H27: 0.03 | I27: 0.02 | J27: =F27-I27 -> 0 | L27: 0.08 | N27: =L27*F27 -> 0.0016 | Q27: 0.2 | S27: =Q27*F27 -> 0.004 | V27: Impact: | W27: -0.0465
E28: Exclusif 21 | F28: 0 | H28: 0.05 | I28: 0.03 | J28: =F28-I28 -> -0.03 | L28: =L9 -> 0.03 | N28: =L28*F28 -> 0 | Q28: =Q9 -> 0.1 | S28: =Q28*F28 -> 0
B29: Bonds: | C29: 0.8 | D29: =SUM(F29:F32) -> 0.42 | E29: Dharma Bonds | F29: 0.3 | H29: 0.3 | I29: 0.3 | J29: =F29-I29 -> 0 | L29: =L10 -> 0.035 | N29: =L29*F29 -> 0.0105 | Q29: =Q10 -> 0.055 | S29: =Q29*F29 -> 0.0165 | V29: 2nd Worst: | W29: Lehman Crisis
E30: Muzinich Credit L/S | F30: 0.03 | H30: 0.07 | I30: 0 | J30: =F30-I30 -> 0.03 | L30: =L11 -> 0.025 | N30: =L30*F30 -> 0.00075 | Q30: =Q11 -> 0.08 | S30: =Q30*F30 -> 0.0024 | W30: -0.0411
E31: Arcano Fund | F31: 0.04 | H31: 0 | I31: 0.04 | J31: =F31-I31 -> 0 | L31: =L12 -> 0.04 | N31: =L31*F31 -> 0.0016 | Q31: =Q12 -> 0.02 | S31: =Q31*F31 -> 0.0008
E32: Rendement Euro Plus | F32: 0.05 | H32: 0.05 | I32: 0.07 | J32: =F32-I32 -> -0.02 | L32: =L13 -> 0.04 | N32: =L32*F32 -> 0.002 | Q32: =Q13 -> 0.1 | S32: =Q32*F32 -> 0.005 | V32: 3rd Worst | W32: Equities down 10%.
B33: Alternatives: | C33: 0.25 | D33: =SUM(F33:F37) -> 0.27 | E33: Gold (buy @1180) | F33: 0.05 | H33: 0 | I33: 0 | J33: =F33-I33 -> 0.05 | L33: =L14 -> 0.1 | N33: =L33*F33 -> 0.005 | Q33: =Q14 -> 0.1 | S33: =Q33*F33 -> 0.005 | W33: -0.0392
E34: Tactical | F34: 0.09 | H34: 0.03 | I34: 0.09 | J34: =F34-I34 -> 0 | L34: =L15 -> 0.02 | N34: =L34*F34 -> 0.0018 | Q34: =Q15 -> 0.02 | S34: =Q34*F34 -> 0.0018
E35: Abrax | F35: 0.05 | H35: 0.05 | I35: 0.05 | J35: =F35-I35 -> 0 | L35: =L17 -> 0.05 | N35: =L35*F35 -> 0.0025 | Q35: =Q17 -> 0.04 | S35: =Q35*F35 -> 0.002
E36: Blackwall | F36: 0.04 | H36: 0 | I36: 0 | J36: =F36-I36 -> 0.04 | L36: =L17 -> 0.05 | N36: =L36*F36 -> 0.002 | Q36: =Q16 -> 0.05 | S36: =Q36*F36 -> 0.002
E37: Cimco | F37: 0.04 | H37: 0.04 | I37: 0.04 | J37: =F37-I37 -> 0 | L37: 0.05 | N37: =L37*F37 -> 0.002 | Q37: 0.05 | S37: =Q37*F37 -> 0.002
E38: Commodities Fund | F38: 0 | H38: 0 | I38: 0.04 | J38: =F38-I38 -> -0.04 | L38: =L18 -> 0.05 | N38: =L38*F38 -> 0 | Q38: =Q19 -> 0.15 | S38: =Q38*F38 -> 0
B39: Cash: | C39: 1 | D39: =100%-D33-D29-D26 -> 0.1 | H39: 0.16 | I39: 0.18 | J39: =D39-I39 -> -0.08 | L39: =L19 -> 0.01 | N39: =L39*D39 -> 0.001
G40: 0.1 | Q40: =Q20 -> 0.05 | S40: =Q40*G40 -> 0.005
D41: =D33+D29+D26 -> 0.9
B43: Balanced Profile | L43: 12 Mos E® | N43: =SUM(N46:N60) -> 0.0509 | Q43: =Q23 -> Risk= | S43: =SUM(S46:S61) -> 0.1011 | Y43: =D46/C46 -> 0.67142857
H44: =H24 -> Q2 | I44: =I24 -> Q3 | J44: =J24 -> Delta (Q4-Q3)
B45: Statutory Max | D45: =D25 -> Q4 2016 | E45: Vector | F45: Vector Weight | G45: Active USD Long
B46: Equities: | C46: 0.7 | D46: =SUM(F46:F51) -> 0.47 | E46: Dharma Equities | F46: 0.38 | H46: 0.42 | I46: 0.42 | J46: =F46-H46 -> -0.04 | L46: =L26 -> 0.06 | N46: =L46*F46 -> 0.0228 | Q46: =Q8 -> 0.15 | S46: =Q46*F46 -> 0.057 | V46: Worst: | W46: Debt Ceiling Crisis 2011
E47: Exclusif 21 | F47: 0 | H47: 0.06 | I47: 0.06 | J47: =F47-H47 -> -0.06 | L47: =L28 -> 0.03 | N47: =L47*F47 -> 0 | Q47: =Q9 -> 0.1 | S47: =Q47*F47 -> 0 | V47: Impact: | W47: -0.0696
E48: TFC Small Caps | F48: 0.03 | H48: 0.03 | I48: 0.04 | J48: =F48-H48 -> 0 | L48: =L27 -> 0.08 | N48: =L48*F48 -> 0.0024 | Q48: =Q27 -> 0.2 | S48: =Q48*F48 -> 0.006
E49: Shanti India | F49: 0.03 | H49: 0.03 | I49: 0.04 | J49: =F49-H49 -> 0 | L49: 0.08 | N49: =L49*F49 -> 0.0024 | Q49: 0.15 | S49: =Q49*F49 -> 0.0045 | V49: 2nd Worst: | W49: Lehman Crisis
E50: Liontrust UK small caps | F50: 0 | H50: ='Q2 16'!I42 -> 0.04 | I50: 0.03 | J50: =F50-H50 -> -0.04 | N50: =L50*F50 -> 0 | S50: =Q50*F50 -> 0 | W50: -0.0689
E51: Liontrust Asian | F51: 0.03 | H51: 0.03 | I51: 0.04 | J51: =F51-H51 -> 0 | L51: 0.08 | N51: =L51*F51 -> 0.0024 | Q51: 0.15 | S51: =Q51*F51 -> 0.0045
B52: Bonds: | C52: 0.5 | D52: =F52+F53 -> 0.18 | E52: Dharma Bonds | F52: 0.18 | H52: ='Q2 16'!I46 -> 0.15 | I52: 0.18 | J52: =F52-H52 -> 0.03 | L52: =L29 -> 0.035 | N52: =L52*F52 -> 0.0063 | Q52: =Q10 -> 0.055 | S52: =Q52*F52 -> 0.0099 | V52: 3rd Worst | W52: Equities down 10%.
E53: Muzinich Credit L/S | F53: 0 | H53: ='Q2 16'!I47 -> 0 | I53: 0 | J53: =F53-H53 -> 0 | L53: =L30 -> 0.025 | N53: =L53*F53 -> 0 | Q53: =Q30 -> 0.08 | S53: =Q53*F53 -> 0 | W53: -0.0674
B54: Alternatives: | C54: 0.3 | D54: =SUM(F54:F59) -> 0.26 | E54: Abrax | F54: 0.05 | H54: ='Q2 16'!I48 -> 0.05 | I54: 0.05 | J54: =F54-H54 -> 0 | L54: =L35 -> 0.05 | N54: =L54*F54 -> 0.0025 | Q54: =Q17 -> 0.04 | S54: =Q54*F54 -> 0.002
E55: Gold (buy @1180) | F55: 0.05 | H55: ='Q2 16'!I49 -> 0 | I55: 0.03 | J55: =F55-H55 -> 0.05 | L55: =L33 -> 0.1 | N55: =L55*F55 -> 0.005 | Q55: =Q33 -> 0.1 | S55: =Q55*F55 -> 0.005
E56: Tactical | F56: 0.06 | H56: ='Q2 16'!I50 -> 0.04 | I56: 0.06 | J56: =F56-H56 -> 0.02 | L56: =L34 -> 0.02 | N56: =L56*F56 -> 0.0012 | Q56: =Q15 -> 0.02 | S56: =Q56*F56 -> 0.0012
E57: Commodities Fund | F57: 0 | H57: 0 | I57: 0.05 | J57: =F57-H57 -> 0 | L57: =L38 -> 0.05 | N57: =L57*F57 -> 0 | Q57: =Q38 -> 0.15 | S57: =Q57*F57 -> 0
E58: Blackwall | F58: 0.05 | H58: 0 | I58: 0 | J58: =F58-H58 -> 0.05 | L58: =L36 -> 0.05 | N58: =L58*F58 -> 0.0025 | Q58: =Q36 -> 0.05 | S58: =Q58*F58 -> 0.0025
E59: Cimco | F59: 0.05 | H59: ='Q2 16'!I52 -> 0.05 | I59: 0.05 | J59: =F59-H59 -> 0 | L59: =L37 -> 0.05 | N59: =L59*F59 -> 0.0025 | Q59: =Q37 -> 0.05 | S59: =Q59*F59 -> 0.0025 | AI59: Estimated Downside Risk
B60: Cash: | C60: 1 | D60: =100%-D54-D52-D46 -> 0.09 | H60: 0.05 | I60: 0.08 | J60: =D60-I60 -> 0.01 | L60: =L39 -> 0.01 | N60: =L60*D60 -> 0.0009
G61: 0.12 | Q61: =Q40 -> 0.05 | S61: =Q61*G61 -> 0.006

Sheet Q4.1 16
S1: Estimated Downside Risk
N2: Return | S2: Average Correction
B3: Q4.1 16 Allocation | S3: Correl=1
M4: 12 Mos E® | O4: =SUM(O8:O20) -> 0.0374 | R4: Risk= | T4: =SUM(T8:T20) -> 0.0646
B5: Income Profile
H6: Q2 | I6: Q3 | J6: Q4 | K6: Delta (Q4.1-Q4)
B7: Statutory Max | D7: Q4.1 2016 | E7: Vector | F7: Vector Weight | G7: Active USD Long
B8: Equities: | C8: 0.2 | D8: =F8+F9 -> 0.15 | E8: Dharma Equities | F8: 0.15 | H8: ='Q2 16'!F7 -> 0.1 | I8: 0.11 | J8: 0.11 | K8: =F8-J8 -> 0.04 | M8: 0.06 | O8: =M8*F8 -> 0.009 | R8: 0.15 | T8: =R8*F8 -> 0.0225
E9: Exclusif 21 | F9: 0 | H9: ='Q2 16'!F8 -> 0.06 | I9: 0.05 | J9: 0 | K9: =F9-J9 -> 0 | M9: 0.03 | O9: =M9*F9 -> 0 | R9: 0.1 | T9: =R9*F9 -> 0
B10: Bonds: | C10: 1 | D10: =SUM(F10:F13) -> 0.56 | E10: Dharma Bonds | F10: 0.4 | H10: ='Q2 16'!F9 -> 0.37 | I10: 0.37 | J10: 0.37 | K10: =F10-J10 -> 0.03 | M10: 0.035 | O10: =M10*F10 -> 0.014 | R10: 0.055 | T10: =R10*F10 -> 0.022
E11: Muzinich Credit L/S | F11: 0.06 | H11: ='Q2 16'!F10 -> 0.05 | I11: 0 | J11: 0.06 | K11: =F11-J11 -> 0 | M11: 0.025 | O11: =M11*F11 -> 0.0015 | R11: 0.08 | T11: =R11*F11 -> 0.0048
E12: Arcano Fund | F12: 0.05 | H12: 0 | I12: 0.05 | J12: 0.05 | K12: =F12-J12 -> 0 | M12: 0.04 | O12: =M12*F12 -> 0.002 | R12: 0.02 | T12: =R12*F12 -> 0.001
E13: Rendement Euro Plus | F13: 0.05 | H13: ='Q2 16'!F11 -> 0.1 | I13: 0.09 | J13: 0.05 | K13: =F13-J13 -> 0 | M13: 0.04 | O13: =M13*F13 -> 0.002 | R13: 0.1 | T13: =R13*F13 -> 0.005
B14: Alternatives: | C14: 0.15 | D14: =SUM(F14:F18) -> 0.14 | E14: Gold (buy @1180) | F14: 0 | H14: ='Q2 16'!F12 -> 0.07 | I14: 0 | J14: 0.05 | K14: =F14-J14 -> -0.05 | M14: 0.1 | O14: =M14*F14 -> 0 | R14: 0.1 | T14: =R14*F14 -> 0
E15: Tactical | F15: 0.08 | H15: ='Q2 16'!F13 -> 0.07 | I15: 0.07 | J15: 0.07 | K15: =F15-J15 -> 0.01 | M15: 0.02 | O15: =M15*F15 -> 0.0016 | R15: 0.02 | T15: =R15*F15 -> 0.0016
E16: Blackwall | F16: 0.03 | H16: 0 | I16: 0 | J16: 0.03 | K16: =F16-J16 -> 0 | M16: 0.06 | O16: =M16*F16 -> 0.0018 | R16: 0.05 | T16: =R16*F16 -> 0.0015
E17: Abrax | F17: 0.03 | H17: ='Q2 16'!F14 -> 0.03 | I17: 0.03 | J17: 0.03 | K17: =F17-J17 -> 0 | M17: 0.05 | O17: =M17*F17 -> 0.0015 | R17: 0.04 | T17: =R17*F17 -> 0.0012
E18: Commodities Fund | F18: 0 | H18: ='Q2 16'!F15 -> 0 | I18: 0.03 | J18: 0 | K18: =F18-J18 -> 0 | M18: 0.05 | O18: =M18*F18 -> 0 | R18: 0.04 | T18: =R18*F18 -> 0
B19: Cash: | C19: 1 | D19: =100%-D14-D10-D8 -> 0.15 | H19: ='Q2 16'!F16 -> 0 | I19: ='Q3 16'!F18 -> 0 | J19: ='Q4 16'!D19 -> 0.18 | K19: =D19-J19 -> -0.03 | M19: 0.01 | O19: =I19*M19 -> 0 | R19: 0.15
G20: 0.1 | L20: Active ccy | M20: 0.04 | O20: =M20*G20 -> 0.004 | R20: 0.05 | T20: =R20*G20 -> 0.005
B23: Conservative Profile | M23: 12 Mos E® | O23: =SUM(O26:O39) -> 0.0399 | R23: =R4 -> Risk= | T23: =SUM(T26:T40) -> 0.07755
H24: =H6 -> Q2 | I24: =I6 -> Q3 | J24: Q4 | K24: =K6 -> Delta (Q4.1-Q4)
B25: Statutory Max | D25: =D7 -> Q4.1 2016 | E25: Vector | F25: Vector Weight | G25: Active USD Long
B26: Equities: | C26: 0.3 | D26: =F26+F28+F27 -> 0.25 | E26: Dharma Equities | F26: 0.23 | H26: 0.22 | I26: 0.18 | J26: ='Q4 16'!F26 -> 0.19 | K26: =F26-J26 -> 0.04 | M26: =M8 -> 0.06 | O26: =M26*F26 -> 0.0138 | R26: =R8 -> 0.15 | T26: =R26*F26 -> 0.0345
E27: TFC Small Caps | F27: 0.02 | H27: 0.03 | I27: 0.02 | J27: ='Q4 16'!F27 -> 0.02 | K27: =F27-J27 -> 0 | M27: 0.08 | O27: =M27*F27 -> 0.0016 | R27: 0.2 | T27: =R27*F27 -> 0.004
E28: Exclusif 21 | F28: 0 | H28: 0.05 | I28: 0.03 | J28: ='Q4 16'!F28 -> 0 | K28: =F28-J28 -> 0 | M28: =M9 -> 0.03 | O28: =M28*F28 -> 0 | R28: =R9 -> 0.1 | T28: =R28*F28 -> 0
B29: Bonds: | C29: 0.8 | D29: =SUM(F29:F32) -> 0.43 | E29: Dharma Bonds | F29: 0.31 | H29: 0.3 | I29: 0.3 | J29: ='Q4 16'!F29 -> 0.3 | K29: =F29-J29 -> 0.01 | M29: =M10 -> 0.035 | O29: =M29*F29 -> 0.01085 | R29: =R10 -> 0.055 | T29: =R29*F29 -> 0.01705
E30: Muzinich Credit L/S | F30: 0.03 | H30: 0.07 | I30: 0 | J30: ='Q4 16'!F30 -> 0.03 | K30: =F30-J30 -> 0 | M30: =M11 -> 0.025 | O30: =M30*F30 -> 0.00075 | R30: =R11 -> 0.08 | T30: =R30*F30 -> 0.0024
E31: Arcano Fund | F31: 0.04 | H31: 0 | I31: 0.04 | J31: ='Q4 16'!F31 -> 0.04 | K31: =F31-J31 -> 0 | M31: =M12 -> 0.04 | O31: =M31*F31 -> 0.0016 | R31: =R12 -> 0.02 | T31: =R31*F31 -> 0.0008
E32: Rendement Euro Plus | F32: 0.05 | H32: 0.05 | I32: 0.07 | J32: ='Q4 16'!F32 -> 0.05 | K32: =F32-J32 -> 0 | M32: =M13 -> 0.04 | O32: =M32*F32 -> 0.002 | R32: =R13 -> 0.1 | T32: =R32*F32 -> 0.005
B33: Alternatives: | C33: 0.25 | D33: =SUM(F33:F37) -> 0.22 | E33: Gold (buy @1180) | F33: 0 | H33: 0 | I33: 0 | J33: ='Q4 16'!F33 -> 0.05 | K33: =F33-J33 -> -0.05 | M33: =M14 -> 0.1 | O33: =M33*F33 -> 0 | R33: =R14 -> 0.1 | T33: =R33*F33 -> 0
E34: Tactical | F34: 0.09 | H34: 0.03 | I34: 0.09 | J34: ='Q4 16'!F34 -> 0.09 | K34: =F34-J34 -> 0 | M34: =M15 -> 0.02 | O34: =M34*F34 -> 0.0018 | R34: =R15 -> 0.02 | T34: =R34*F34 -> 0.0018
E35: Abrax | F35: 0.05 | H35: 0.05 | I35: 0.05 | J35: ='Q4 16'!F35 -> 0.05 | K35: =F35-J35 -> 0 | M35: =M17 -> 0.05 | O35: =M35*F35 -> 0.0025 | R35: =R17 -> 0.04 | T35: =R35*F35 -> 0.002
E36: Blackwall | F36: 0.04 | H36: 0 | I36: 0 | J36: ='Q4 16'!F36 -> 0.04 | K36: =F36-J36 -> 0 | M36: =M17 -> 0.05 | O36: =M36*F36 -> 0.002 | R36: =R16 -> 0.05 | T36: =R36*F36 -> 0.002
E37: Cimco | F37: 0.04 | H37: 0.04 | I37: 0.04 | J37: ='Q4 16'!F37 -> 0.04 | K37: =F37-J37 -> 0 | M37: 0.05 | O37: =M37*F37 -> 0.002 | R37: 0.05 | T37: =R37*F37 -> 0.002
E38: Commodities Fund | F38: 0 | H38: 0 | I38: 0.04 | J38: ='Q4 16'!F38 -> 0 | K38: =F38-J38 -> 0 | M38: =M18 -> 0.05 | O38: =M38*F38 -> 0 | R38: =R19 -> 0.15 | T38: =R38*F38 -> 0
B39: Cash: | C39: 1 | D39: =100%-D33-D29-D26 -> 0.1 | H39: 0.16 | I39: 0.18 | J39: ='Q4 16'!D39 -> 0.1 | K39: =D39-J39 -> 0 | M39: =M19 -> 0.01 | O39: =M39*D39 -> 0.001
G40: 0.12 | R40: =R20 -> 0.05 | T40: =R40*G40 -> 0.006
B43: Balanced Profile | M43: 12 Mos E® | O43: =SUM(O46:O60) -> 0.0485 | R43: =R23 -> Risk= | T43: =SUM(T46:T61) -> 0.1038
H44: =H24 -> Q2 | I44: =I24 -> Q3 | J44: Q4 | K44: =K24 -> Delta (Q4.1-Q4)
B45: Statutory Max | D45: =D25 -> Q4.1 2016 | E45: Vector | F45: Vector Weight | G45: Active USD Long
B46: Equities: | C46: 0.7 | D46: =SUM(F46:F51) -> 0.51 | E46: Dharma Equities | F46: 0.42 | H46: 0.42 | I46: 0.42 | J46: ='Q4 16'!F46 -> 0.38 | K46: =F46-J46 -> 0.04 | M46: =M26 -> 0.06 | O46: =M46*F46 -> 0.0252 | R46: =R8 -> 0.15 | T46: =R46*F46 -> 0.063
E47: Exclusif 21 | F47: 0 | H47: 0.06 | I47: 0.06 | J47: ='Q4 16'!F47 -> 0 | K47: =F47-J47 -> 0 | M47: =M28 -> 0.03 | O47: =M47*F47 -> 0 | R47: =R9 -> 0.1 | T47: =R47*F47 -> 0
E48: TFC Small Caps | F48: 0.03 | H48: 0.03 | I48: 0.04 | J48: ='Q4 16'!F48 -> 0.03 | K48: =F48-J48 -> 0 | M48: =M27 -> 0.08 | O48: =M48*F48 -> 0.0024 | R48: =R27 -> 0.2 | T48: =R48*F48 -> 0.006
E49: Shanti India | F49: 0.03 | H49: 0.03 | I49: 0.04 | J49: ='Q4 16'!F49 -> 0.03 | K49: =F49-J49 -> 0 | M49: 0.08 | O49: =M49*F49 -> 0.0024 | R49: 0.15 | T49: =R49*F49 -> 0.0045
E50: Liontrust UK small caps | F50: 0 | H50: ='Q2 16'!F42 -> 0.04 | I50: 0.03 | J50: ='Q4 16'!F50 -> 0 | K50: =F50-J50 -> 0 | O50: =M50*F50 -> 0 | T50: =R50*F50 -> 0
E51: Liontrust Asian | F51: 0.03 | H51: 0.03 | I51: 0.04 | J51: ='Q4 16'!F51 -> 0.03 | K51: =F51-J51 -> 0 | M51: 0.08 | O51: =M51*F51 -> 0.0024 | R51: 0.15 | T51: =R51*F51 -> 0.0045
B52: Bonds: | C52: 0.5 | D52: =F52+F53 -> 0.18 | E52: Dharma Bonds | F52: 0.18 | H52: ='Q2 16'!F46 -> 0.15 | I52: 0.18 | J52: ='Q4 16'!F52 -> 0.18 | K52: =F52-J52 -> 0 | M52: =M29 -> 0.035 | O52: =M52*F52 -> 0.0063 | R52: =R10 -> 0.055 | T52: =R52*F52 -> 0.0099
E53: Muzinich Credit L/S | F53: 0 | H53: ='Q2 16'!F47 -> 0 | I53: 0 | J53: ='Q4 16'!F53 -> 0 | K53: =F53-J53 -> 0 | M53: =M30 -> 0.025 | O53: =M53*F53 -> 0 | R53: =R30 -> 0.08 | T53: =R53*F53 -> 0
B54: Alternatives: | C54: 0.3 | D54: =SUM(F54:F59) -> 0.22 | E54: Abrax | F54: 0.05 | H54: ='Q2 16'!F48 -> 0.05 | I54: 0.05 | J54: ='Q4 16'!F54 -> 0.05 | K54: =F54-J54 -> 0 | M54: =M35 -> 0.05 | O54: =M54*F54 -> 0.0025 | R54: =R17 -> 0.04 | T54: =R54*F54 -> 0.002
E55: Gold (buy @1180) | F55: 0 | H55: ='Q2 16'!F49 -> 0.03 | I55: 0.03 | J55: ='Q4 16'!F55 -> 0.05 | K55: =F55-J55 -> -0.05 | M55: =M33 -> 0.1 | O55: =M55*F55 -> 0 | R55: =R33 -> 0.1 | T55: =R55*F55 -> 0
E56: Tactical | F56: 0.07 | H56: ='Q2 16'!F50 -> 0.06 | I56: 0.06 | J56: ='Q4 16'!F56 -> 0.06 | K56: =F56-J56 -> 0.01 | M56: =M34 -> 0.02 | O56: =M56*F56 -> 0.0014 | R56: =R15 -> 0.02 | T56: =R56*F56 -> 0.0014
E57: Commodities Fund | F57: 0 | H57: 0 | I57: 0.05 | J57: ='Q4 16'!F57 -> 0 | K57: =F57-J57 -> 0 | M57: =M38 -> 0.05 | O57: =M57*F57 -> 0 | R57: =R38 -> 0.15 | T57: =R57*F57 -> 0
E58: Blackwall | F58: 0.05 | H58: 0 | I58: 0 | J58: ='Q4 16'!F58 -> 0.05 | K58: =F58-J58 -> 0 | M58: =M36 -> 0.05 | O58: =M58*F58 -> 0.0025 | R58: =R36 -> 0.05 | T58: =R58*F58 -> 0.0025
E59: Cimco | F59: 0.05 | H59: ='Q2 16'!F52 -> 0.05 | I59: 0.05 | J59: ='Q4 16'!F59 -> 0.05 | K59: =F59-J59 -> 0 | M59: =M37 -> 0.05 | O59: =M59*F59 -> 0.0025 | R59: =R37 -> 0.05 | T59: =R59*F59 -> 0.0025
B60: Cash: | C60: 1 | D60: =100%-D54-D52-D46 -> 0.09 | H60: 0.05 | I60: 0.08 | J60: ='Q4 16'!D60 -> 0.09 | K60: =D60-J60 -> 1.110223e-16 | M60: =M39 -> 0.01 | O60: =M60*D60 -> 0.0009
G61: 0.15 | R61: =R40 -> 0.05 | T61: =R61*G61 -> 0.0075

Sheet Q1 17
Q1: Estimated Downside Risk | U1: Bloomberg Scenario
L2: Return | Q2: Average Correction | U2: Risk
B3: Q1 17 Allocation | Q3: Correl=1
K4: 12 Mos E® | M4: =SUM(M8:M26) -> 0.03635 | P4: Risk= | R4: =SUM(R8:R26) -> 0.06365 | X4: =D8/C8 -> 1 | Y4: Potential
B5: Income Profile
H6: Q4 16 | I6: Delta (Q1-Q4) | AB6: =SUM(AB8:AB77) -> 0
B7: Statutory Max | D7: Q1 2017 | E7: Vector | F7: Vector Weight | G7: Active USD Long | U7: Worst: | V7: EUR up 10% vs USD
B8: Equities: | C8: 0.2 | D8: =SUM(F8:F10) -> 0.2 | E8: Dharma Equities | F8: 0.12 | H8: ='Q4 16'!F8 -> 0.11 | I8: =F8-H8 -> 0.01 | K8: 0.06 | M8: =K8*F8 -> 0.0072 | P8: 0.15 | R8: =P8*F8 -> 0.018 | U8: Impact: | V8: -0.0407 | Z8: =20000000 -> 20000000 | AB8: =Z8*F22 -> 0
E9: Tactical | F9: 0.05 | H9: ='Q4 16'!F15 -> 0.07 | I9: =F9-H9 -> -0.02 | K9: 0.02 | M9: =K9*F9 -> 0.001 | P9: 0.02 | R9: =P9*F9 -> 0.001
E10: Shanti Equities | F10: 0.03 | H10: ='Q4 16'!F9 -> 0 | I10: =F10-H10 -> 0.03 | K10: 0.08 | M10: =K10*F10 -> 0.0024 | P10: 0.18 | R10: =P10*F10 -> 0.0054
B11: Bonds: | C11: 1 | D11: =SUM(F11:F17) -> 0.53 | E11: Dharma Bonds | F11: 0.35 | H11: ='Q4 16'!F10 -> 0.37 | I11: =F11-H11 -> -0.02 | K11: 0.035 | M11: =K11*F11 -> 0.01225 | P11: 0.055 | R11: =P11*F11 -> 0.01925 | U11: 2nd Worst: | V11: Lehman Crisis
E12: Muzinich Credit L/S | F12: 0.03 | H12: ='Q4 16'!F11 -> 0.06 | I12: =F12-H12 -> -0.03 | K12: 0.025 | M12: =K12*F12 -> 0.00075 | P12: 0.08 | R12: =P12*F12 -> 0.0024 | V12: -0.029
E13: Pictet EM LCL | F13: 0 | H13: 0 | I13: =F13-H13 -> 0 | K13: 0.04 | M13: =K13*F13 -> 0 | P13: 0.12 | R13: =P13*F13 -> 0
E14: Muzinich Global Tactical | F14: 0.04 | H14: 0 | I14: =F14-H14 -> 0.04 | K14: 0.03 | M14: =K14*F14 -> 0.0012 | P14: 0.025 | R14: =P14*F14 -> 0.001
E15: Muzinich Short Dur HY | F15: 0.02 | H15: 0 | I15: =F15-H15 -> 0.02 | K15: 0.03 | M15: =K15*F15 -> 0.0006 | P15: 0.07 | R15: =P15*F15 -> 0.0014
E16: Hybrid Exane Basket | F16: 0.04 | H16: 0 | I16: =F16-H16 -> 0.04 | K16: 0.06 | M16: =K16*F16 -> 0.0024 | P16: =8% -> 0.08 | R16: =P16*F16 -> 0.0032
E17: Rendement Euro Plus | F17: 0.05 | H17: ='Q4 16'!F13 -> 0.05 | I17: =F17-H17 -> 0 | K17: 0.04 | M17: =K17*F17 -> 0.002 | P17: 0.1 | R17: =P17*F17 -> 0.005 | U17: 3rd Worst | V17: Equities down 10%.
B18: Alternatives: | C18: 0.15 | D18: =SUM(F18:F24) -> 0.11 | E18: Gold | F18: 0.03 | H18: ='Q4 16'!F14 -> 0.05 | I18: =F18-H18 -> -0.02 | K18: 0.1 | M18: =K18*F18 -> 0.003 | P18: 0.1 | R18: =P18*F18 -> 0.003 | V18: -0.0277
E19: Arcano Fund | F19: 0.05 | H19: ='Q4 16'!F12 -> 0.05 | I19: =F19-H19 -> 0 | K19: 0.035 | M19: =K19*F19 -> 0.00175 | P19: 0.05 | R19: =P19*F19 -> 0.0025 | Y19: 0.02
E20: Blackwall | F20: 0.03 | H20: ='Q4 16'!F16 -> 0.03 | I20: =F20-H20 -> 0 | K20: 0.06 | M20: =K20*F20 -> 0.0018 | P20: 0.05 | R20: =P20*F20 -> 0.0015
E21: Loan Fund | F21: 0 | H21: 0 | I21: =F21-H21 -> 0 | K21: 0.075 | M21: =K21*F21 -> 0 | P21: 0.1 | R21: =P21*F21 -> 0 | Y21: 0.04
E22: CTA | F22: 0 | H22: 0 | I22: =F22-H22 -> 0 | K22: 0.08 | M22: =K22*F22 -> 0 | P22: 0.12 | R22: =P22*F22 -> 0 | Y22: 0.02
E23: Abrax | F23: 0 | H23: ='Q4 16'!F17 -> 0.03 | I23: =F23-H23 -> -0.03 | K23: 0.05 | M23: =K23*F23 -> 0 | P23: 0.04 | R23: =P23*F23 -> 0
E24: Commodities Fund | F24: 0 | H24: ='Q4 16'!F18 -> 0 | I24: =F24-H24 -> 0 | K24: 0.05 | M24: =K24*F24 -> 0 | P24: 0.04 | R24: =P24*F24 -> 0 | Y24: 0.03
B25: Cash: | C25: 1 | D25: =100%-D18-D11-D8 -> 0.16 | H25: ='Q4 16'!D19 -> 0.18 | I25: =D25-'Q4 16'!D19 -> -0.02 | K25: 0 | M25: =K25*D25 -> 0 | P25: 0
G26: 0 | J26: Active ccy | K26: 0.04 | M26: =K26*G26 -> 0 | P26: 0.05 | R26: =P26*G26 -> 0
B29: Conservative Profile | K29: 12 Mos E® | M29: =SUM(M32:M52) -> 0.043 | P29: =P4 -> Risk= | R29: =SUM(R32:R53) -> 0.0733 | X29: =D32/C32 -> 1 | Y29: Potential
H30: =H6 -> Q4 16 | I30: =I6 -> Delta (Q1-Q4) | Z30: =60000000 -> 60000000 | AB30: =Z30*F47 -> 0
B31: Statutory Max | D31: =D7 -> Q1 2017 | E31: Vector | F31: Vector Weight | G31: Active USD Long
B32: Equities: | C32: 0.3 | D32: =SUM(F32:F37) -> 0.3 | E32: Dharma Equities | F32: 0.19 | H32: ='Q4 16'!F26 -> 0.19 | I32: =F32-H32 -> 0 | K32: =K8 -> 0.06 | M32: =K32*F32 -> 0.0114 | P32: =P8 -> 0.15 | R32: =P32*F32 -> 0.0285 | U32: Worst: | V32: EUR up 10% vs USD
E33: TFC Small Caps | F33: 0 | H33: ='Q4 16'!F27 -> 0.02 | I33: =F33-H33 -> -0.02 | K33: 0.08 | M33: =K33*F33 -> 0 | P33: 0.2 | R33: =P33*F33 -> 0 | U33: Impact: | V33: -0.0465
E34: Tactical | F34: 0.04 | H34: 0.03 | I34: =F34-H34 -> 0.01 | K34: =K9 -> 0.02 | M34: =K34*F34 -> 0.0008 | P34: =P9 -> 0.02 | R34: =P34*F34 -> 0.0008
E35: Quadra | F35: 0.02 | H35: 0 | I35: =F35-H35 -> 0.02 | K35: 0.08 | M35: =K35*F35 -> 0.0016 | P35: 0.07 | R35: =P35*F35 -> 0.0014
E36: Shanti Equities | F36: 0.02 | H36: 0 | I36: =F36-H36 -> 0.02 | K36: 0.08 | M36: =K36*F36 -> 0.0016 | P36: 0.18 | R36: =P36*F36 -> 0.0036
E37: Liontrust Asia | F37: 0.03 | H37: ='Q4 16'!F28 -> 0 | I37: =F37-H37 -> 0.03 | K37: =K10 -> 0.08 | M37: =K37*F37 -> 0.0024 | P37: =P10 -> 0.18 | R37: =P37*F37 -> 0.0054
B38: Bonds: | C38: 0.8 | D38: =SUM(F38:F42) -> 0.38 | E38: Dharma Bonds | F38: 0.3 | H38: ='Q4 16'!F29 -> 0.3 | I38: =F38-H38 -> 0 | K38: =K11 -> 0.035 | M38: =K38*F38 -> 0.0105 | P38: =P11 -> 0.055 | R38: =P38*F38 -> 0.0165 | U38: 2nd Worst: | V38: Lehman Crisis
E39: Muzinich Global Tactical | F39: 0.04 | H39: 0 | I39: =F39-H39 -> 0.04 | K39: 0.03 | M39: =K39*F39 -> 0.0012 | P39: 0.025 | R39: =P39*F39 -> 0.001 | V39: -0.0411
E40: Pictet LCL EM | F40: 0 | H40: 0 | I40: =F40-H40 -> 0 | K40: =K13 -> 0.04 | M40: =K40*F40 -> 0 | P40: =P13 -> 0.12 | R40: =P40*F40 -> 0
E41: Muzinich Short Dur HY | F41: 0 | H41: 0 | I41: =F41-H41 -> 0 | K41: =K15 -> 0.03 | M41: =K41*F41 -> 0 | P41: =P15 -> 0.07 | R41: =P41*F41 -> 0
E42: Rendement Euro Plus | F42: 0.04 | H42: ='Q4 16'!F32 -> 0.05 | I42: =F42-H42 -> -0.01 | K42: =K17 -> 0.04 | M42: =K42*F42 -> 0.0016 | P42: =P17 -> 0.1 | R42: =P42*F42 -> 0.004 | U42: 3rd Worst | V42: Equities down 10%.
B43: Alternatives: | C43: 0.25 | D43: =SUM(F43:F51) -> 0.2 | E43: Gold | F43: 0.03 | H43: 0 | I43: =F43-H43 -> 0.03 | K43: =K18 -> 0.1 | M43: =K43*F43 -> 0.003 | P43: =P18 -> 0.1 | R43: =P43*F43 -> 0.003 | V43: -0.0392 | Y43: 0.02
E44: Loan Fund | F44: 0 | H44: 0 | I44: =F44-H44 -> 0 | K44: =K21 -> 0.075 | M44: =K44*F44 -> 0 | P44: =P21 -> 0.1 | R44: =P44*F44 -> 0 | Y44: 0.04
E45: Abrax | F45: 0.04 | H45: 0.05 | I45: =F45-H45 -> -0.01 | K45: =K23 -> 0.05 | M45: =K45*F45 -> 0.002 | P45: =P23 -> 0.04 | R45: =P45*F45 -> 0.0016
E46: Arcano Fund | F46: 0.04 | H46: ='Q4 16'!F31 -> 0.04 | I46: =F46-H46 -> 0 | K46: =K19 -> 0.035 | M46: =K46*F46 -> 0.0014 | P46: =P19 -> 0.05 | R46: =P46*F46 -> 0.002 | Y46: 0
E47: CTA | F47: 0 | H47: 0 | I47: =F47-H47 -> 0 | K47: =K22 -> 0.08 | M47: =K47*F47 -> 0 | P47: =P22 -> 0.12 | R47: =P47*F47 -> 0 | Y47: 0.025
E48: Blackwall | F48: 0.04 | H48: 0 | I48: =F48-H48 -> 0.04 | K48: =K23 -> 0.05 | M48: =K48*F48 -> 0.002 | P48: =P20 -> 0.05 | R48: =P48*F48 -> 0.002
E49: Doric | F49: 0.02 | H49: 0 | I49: =F49-H49 -> 0.02 | K49: 0.1 | M49: =K49*F49 -> 0.002 | P49: 0.1 | R49: =P49*F49 -> 0.002
E50: Cimco | F50: 0.03 | H50: 0.04 | I50: =F50-H50 -> -0.01 | K50: 0.05 | M50: =K50*F50 -> 0.0015 | P50: 0.05 | R50: =P50*F50 -> 0.0015
E51: Commodities Fund | F51: 0 | H51: 0 | I51: =F51-H51 -> 0 | K51: =K24 -> 0.05 | M51: =K51*F51 -> 0 | P51: =P25 -> 0 | R51: =P51*F51 -> 0 | Y51: 0.03
B52: Cash: | C52: 1 | D52: =100%-D43-D38-D32 -> 0.12 | H52: 0.16 | I52: =D52-H52 -> -0.04 | K52: =K25 -> 0 | M52: =K52*D52 -> 0
G53: 0 | P53: =P26 -> 0.05 | R53: =P53*G53 -> 0
D54: =D43+D38+D32 -> 0.88
B56: Balanced Profile | K56: 12 Mos E® | M56: =SUM(M59:M76) -> 0.0535 | P56: =P29 -> Risk= | R56: =SUM(R59:R77) -> 0.0998 | X56: =D59/C59 -> 0.8 | Y56: Potential
H57: =H30 -> Q4 16 | I57: =I30 -> Delta (Q1-Q4) | Z57: =20000000 -> 20000000 | AB57: =F71*Z57 -> 0
B58: Statutory Max | D58: =D31 -> Q1 2017 | E58: Vector | F58: Vector Weight | G58: Active USD Long
B59: Equities: | C59: 0.7 | D59: =SUM(F59:F65) -> 0.56 | E59: Dharma Equities | F59: 0.38 | H59: 0.42 | I59: =F59-H59 -> -0.04 | K59: =K32 -> 0.06 | M59: =K59*F59 -> 0.0228 | P59: =P8 -> 0.15 | R59: =P59*F59 -> 0.057 | U59: Worst: | V59: Debt Ceiling Crisis 2011
F60: 0 | H60: 0.06 | I60: =F60-H60 -> -0.06 | K60: =K37 -> 0.08 | M60: =K60*F60 -> 0 | P60: =P10 -> 0.18 | R60: =P60*F60 -> 0 | U60: Impact: | V60: -0.0696
E61: TFC Small Caps | F61: 0.02 | H61: 0.03 | I61: =F61-H61 -> -0.01 | K61: =K33 -> 0.08 | M61: =K61*F61 -> 0.0016 | P61: =P33 -> 0.2 | R61: =P61*F61 -> 0.004
E62: Tactical | F62: 0.05 | H62: ='Q2 16'!I50 -> 0.04 | I62: =F62-H62 -> 0.01 | K62: =K34 -> 0.02 | M62: =K62*F62 -> 0.001 | P62: =P9 -> 0.02 | R62: =P62*F62 -> 0.001
E63: Shanti Equities | F63: 0.03 | H63: 0.03 | I63: =F63-H63 -> 0 | K63: =K36 -> 0.08 | M63: =K63*F63 -> 0.0024 | P63: =P36 -> 0.18 | R63: =P63*F63 -> 0.0054 | U63: 2nd Worst: | V63: Lehman Crisis
E64: Quadra | F64: 0.04 | H64: 0 | I64: =F64-H64 -> 0.04 | K64: =K35 -> 0.08 | M64: =K64*F64 -> 0.0032 | P64: =P35 -> 0.07 | R64: =P64*F64 -> 0.0028
E65: Liontrust Asian | F65: 0.04 | H65: 0.03 | I65: =F65-H65 -> 0.01 | K65: =K37 -> 0.08 | M65: =K65*F65 -> 0.0032 | P65: =P37 -> 0.18 | R65: =P65*F65 -> 0.0072
B66: Bonds: | C66: 0.5 | D66: =F66+F67 -> 0.18 | E66: Dharma Bonds | F66: 0.18 | H66: ='Q2 16'!I46 -> 0.15 | I66: =F66-H66 -> 0.03 | K66: =K38 -> 0.035 | M66: =K66*F66 -> 0.0063 | P66: =P11 -> 0.055 | R66: =P66*F66 -> 0.0099 | U66: 3rd Worst | V66: Equities down 10%.
E67: Muzinich Global Tactical | F67: 0 | H67: 0 | I67: =F67-H67 -> 0 | K67: 0.03 | M67: =K67*F67 -> 0 | P67: 0.025 | R67: =P67*F67 -> 0 | V67: -0.0674
B68: Alternatives: | C68: 0.3 | D68: =SUM(F68:F75) -> 0.19 | E68: Abrax | F68: 0.05 | H68: ='Q2 16'!I48 -> 0.05 | I68: =F68-H68 -> 0 | K68: =K45 -> 0.05 | M68: =K68*F68 -> 0.0025 | P68: =P23 -> 0.04 | R68: =P68*F68 -> 0.002
E69: Gold | F69: 0.03 | H69: ='Q2 16'!I49 -> 0 | I69: =F69-H69 -> 0.03 | K69: =K43 -> 0.1 | M69: =K69*F69 -> 0.003 | P69: =P43 -> 0.1 | R69: =P69*F69 -> 0.003
E70: Commodities Fund | F70: 0 | H70: 0 | I70: =F70-H70 -> 0 | K70: =K51 -> 0.05 | M70: =K70*F70 -> 0 | P70: =P51 -> 0 | R70: =P70*F70 -> 0 | Y70: 0.04
E71: CTA | F71: 0 | H71: 0 | I71: =F71-H71 -> 0 | K71: =K47 -> 0.08 | M71: =M47 -> 0 | P71: =P47 -> 0.12 | R71: =P71*F71 -> 0 | Y71: 0.03
E72: Doric | F72: 0.04 | H72: 0 | I72: =F72-H72 -> 0.04 | K72: =K49 -> 0.1 | M72: =K72*F72 -> 0.004 | P72: =P49 -> 0.1 | R72: =P72*F72 -> 0.004
E73: Loan Fund | F73: 0 | H73: 0 | I73: =F73-H73 -> 0 | K73: =K44 -> 0.075 | M73: =K73*F73 -> 0 | P73: =P44 -> 0.1 | R73: =P73*F73 -> 0 | Y73: 0.05
E74: Blackwall | F74: 0.04 | H74: 0 | I74: =F74-H74 -> 0.04 | K74: =K48 -> 0.05 | M74: =K74*F74 -> 0.002 | P74: =P48 -> 0.05 | R74: =P74*F74 -> 0.002
E75: Cimco | F75: 0.03 | H75: ='Q2 16'!I52 -> 0.05 | I75: =F75-H75 -> -0.02 | K75: =K50 -> 0.05 | M75: =K75*F75 -> 0.0015 | P75: =P50 -> 0.05 | R75: =P75*F75 -> 0.0015
B76: Cash: | C76: 1 | D76: =100%-D68-D66-D59 -> 0.07 | H76: 0.05 | I76: =D76-H76 -> 0.02 | K76: =K52 -> 0 | M76: =K76*D76 -> 0
G77: 0 | P77: =P53 -> 0.05 | R77: =P77*G77 -> 0

Sheet Q1 16
B3: Q1 16 Allocation
B6: Income Profile
B8: Statutory Max | F8: Allocations Q12016 | H8: Vector | I8: Vector Weight | K8: Active USD Long
C9: Equities: | D9: 0.2 | F9: =I9+I10 -> 0.2 | H9: Cell D | I9: 0.15
H10: Exclusif 21 | I10: 0.05
C11: Bonds: | F11: =I11+I12+I13 -> 0.55 | H11: Cell C | I11: 0.4
H12: KKR | I12: 0.08
H13: TFC Bonds | I13: 0.07
C14: Alternatives: | F14: =SUM(I14:I17) -> 0.1 | H14: Loan fund | I14: 0
H15: Tactical | I15: 0.07
H16: Abrax | I16: 0.03
H17: Syquant | I17: 0
C18: Cash: | F18: =100%-F14-F11-F9 -> 0.15
K19: 10 to 15%
B24: Conservative Profile
B26: Statutory Max | F26: Allocations Q12016 | H26: Vector | I26: Vector Weight | K26: Active USD Long
C27: Equities: | D27: 0.3 | F27: =I27+I29+I28 -> 0.3 | H27: Cell D | I27: 0.22
H28: TFC Small Caps | I28: 0.03
H29: Exclusif 21 | I29: 0.05
C30: Bonds: | F30: =I30+I31+I32 -> 0.42 | H30: Cell C | I30: 0.3
H31: KKR | I31: 0.07
H32: TFC Bonds | I32: 0.05
C33: Alternatives: | F33: =SUM(I33:I37) -> 0.12 | H33: Loan Fund | I33: 0
H34: Tactical | I34: 0.03
H35: Abrax | I35: 0.05
H36: Syquant | I36: 0
H37: Cimco | I37: 0.04
C38: Cash: | F38: =100%-F33-F30-F27 -> 0.16 | K38: 20 to 25%
B43: Balanced Profile
B45: Statutory Max | F45: Allocations Q12016 | H45: Vector | I45: Vector Weight | K45: Active USD Long
C46: Equities: | D46: 0.7 | F46: =I46+I47+I49+I50+I48 -> 0.57 | H46: Cell D | I46: 0.42
H47: Exclusif 21 | I47: 0.06
H48: TFC Small Caps | I48: 0.03
H49: Shanti India | I49: 0.03
H50: Liontrust Asian | I50: 0.03
C51: Bonds: | F51: =I51+I52 -> 0.23 | H51: Cell C | I51: 0.18
H52: KKR | I52: 0.05
C53: Alternatives: | F53: =SUM(I53:I56) -> 0.15 | H53: Abrax | I53: 0.06
H54: Tactical | I54: 0.04 | K54: 20 to 25%
H55: Syquant | I55: 0
H56: Cimco | I56: 0.05
C57: Cash: | F57: =100%-F53-F51-F46 -> 0.05

Sheet Q3 16
R1: Estimated Downside Risk
M2: Return | R2: Average Correction
B3: Q3 16 Allocation | R3: Corr=1
L4: 12 Mos E® | N4: =SUM(N8:N19) -> 0.0296 | Q4: Risk= | S4: =SUM(S8:S19) -> 0.05965
B5: Income Profile
H6: Q2 | I6: Q3 | J6: Delta (Q3-Q2)
B7: Statutory Max | D7: Q3 2016 | E7: Vector | F7: Vector Weight | G7: Active USD Long
B8: Equities: | C8: 0.2 | D8: =F8+F9 -> 0.16 | E8: Cell D | F8: 0.11 | H8: ='[1]Q2 16'!I7 -> 0.13 | I8: =F8 -> 0.11 | J8: =I8-H8 -> -0.02 | L8: 0.05 | N8: =L8*F8 -> 0.0055 | Q8: 0.15 | S8: =Q8*F8 -> 0.0165
E9: Exclusif 21 | F9: 0.05 | H9: ='[1]Q2 16'!I8 -> 0.05 | I9: =F9 -> 0.05 | J9: =I9-H9 -> 0 | L9: 0.03 | N9: =L9*F9 -> 0.0015 | Q9: 0.1 | S9: =Q9*F9 -> 0.005
B10: Bonds: | C10: 1 | D10: =SUM(F10:F13) -> 0.51 | E10: Cell C | F10: 0.37 | H10: ='[1]Q2 16'!I9 -> 0.37 | I10: =F10 -> 0.37 | J10: =I10-H10 -> 0 | L10: 0.03 | N10: =L10*F10 -> 0.0111 | Q10: 0.055 | S10: =Q10*F10 -> 0.02035
E11: KKR NB C L/S TBC | F11: 0 | H11: ='[1]Q2 16'!I10 -> 0.08 | I11: =F11 -> 0 | J11: =I11-H11 -> -0.08 | N11: =L11*F11 -> 0 | S11: =Q11*F11 -> 0
E12: Arcano Fund | F12: 0.05 | H12: 0 | I12: =F12 -> 0.05 | J12: =I12-H12 -> 0.05 | L12: 0.04 | N12: =L12*F12 -> 0.002 | Q12: 0.02 | S12: =Q12*F12 -> 0.001
E13: TFC Bonds | F13: 0.09 | H13: ='[1]Q2 16'!I11 -> 0.1 | I13: =F13 -> 0.09 | J13: =I13-H13 -> -0.01 | L13: 0.03 | N13: =L13*F13 -> 0.0027 | Q13: 0.1 | S13: =Q13*F13 -> 0.009
B14: Alternatives: | C14: 0.15 | D14: =SUM(F14:F17) -> 0.13 | E14: Gold | F14: 0 | H14: ='[1]Q2 16'!I12 -> 0 | I14: =F14 -> 0 | J14: =I14-H14 -> 0 | N14: =L14*F14 -> 0 | S14: =Q14*F14 -> 0
E15: Tactical | F15: 0.07 | H15: ='[1]Q2 16'!I13 -> 0.07 | I15: =F15 -> 0.07 | J15: =I15-H15 -> 0 | L15: 0.02 | N15: =L15*F15 -> 0.0014 | Q15: 0.02 | S15: =Q15*F15 -> 0.0014
E16: Abrax | F16: 0.03 | H16: ='[1]Q2 16'!I14 -> 0.03 | I16: =F16 -> 0.03 | J16: =I16-H16 -> 0 | L16: 0.05 | N16: =L16*F16 -> 0.0015 | Q16: 0.04 | S16: =Q16*F16 -> 0.0012
E17: Commodities Fund | F17: 0.03 | H17: ='[1]Q2 16'!I15 -> 0 | I17: =F17 -> 0.03 | J17: =I17-H17 -> 0.03 | L17: 0.05 | N17: =L17*F17 -> 0.0015 | Q17: 0.04 | S17: =Q17*F17 -> 0.0012
B18: Cash: | C18: 1 | D18: =100%-D14-D10-D8 -> 0.2 | G18: 0.08 | H18: ='[1]Q2 16'!I16 -> 0.17 | I18: =D18 -> 0.2 | J18: =I18-H18 -> 0.03 | L18: -0.004 | N18: =I18*L18 -> -0.0008
K19: Active ccy | L19: 0.04 | N19: =L19*G18 -> 0.0032 | Q19: 0.05 | S19: =Q19*G18 -> 0.004
B22: Conservative Profile | L22: 12 Mos E® | N22: =SUM(N25:N38) -> 0.03138 | Q22: =Q4 -> Risk= | S22: =SUM(S25:S39) -> 0.0707
H23: =H6 -> Q2 | I23: =I6 -> Q3 | J23: =J6 -> Delta (Q3-Q2)
B24: Statutory Max | D24: =D7 -> Q3 2016 | E24: Vector | F24: Vector Weight | G24: Active USD Long
B25: Equities: | C25: 0.3 | D25: =F25+F27+F26 -> 0.23 | E25: Cell D | F25: 0.18 | H25: 0.22 | I25: =F25 -> 0.18 | J25: =I25-H25 -> -0.04 | L25: =L8 -> 0.05 | N25: =L25*F25 -> 0.009 | Q25: =Q8 -> 0.15 | S25: =Q25*F25 -> 0.027
E26: TFC Small Caps | F26: 0.02 | H26: 0.03 | I26: =F26 -> 0.02 | J26: =I26-H26 -> -0.01 | L26: 0.06 | N26: =L26*F26 -> 0.0012 | Q26: 0.2 | S26: =Q26*F26 -> 0.004
E27: Exclusif 21 | F27: 0.03 | H27: 0.05 | I27: =F27 -> 0.03 | J27: =I27-H27 -> -0.02 | L27: =L9 -> 0.03 | N27: =L27*F27 -> 0.0009 | Q27: =Q9 -> 0.1 | S27: =Q27*F27 -> 0.003
B28: Bonds: | C28: 0.8 | D28: =SUM(F28:F31) -> 0.41 | E28: Cell C | F28: 0.3 | H28: 0.3 | I28: =F28 -> 0.3 | J28: =I28-H28 -> 0 | L28: =L10 -> 0.03 | N28: =L28*F28 -> 0.009 | Q28: =Q10 -> 0.055 | S28: =Q28*F28 -> 0.0165
E29: KKR NB C L/S TBC | F29: 0 | H29: 0.07 | I29: =F29 -> 0 | J29: =I29-H29 -> -0.07 | N29: =L29*F29 -> 0 | S29: =Q29*F29 -> 0
E30: Arcano Fund | F30: 0.04 | H30: 0 | I30: =F30 -> 0.04 | J30: =I30-H30 -> 0.04 | L30: =L12 -> 0.04 | N30: =L30*F30 -> 0.0016 | Q30: =Q12 -> 0.02 | S30: =Q30*F30 -> 0.0008
E31: TFC Bonds | F31: 0.07 | H31: 0.05 | I31: =F31 -> 0.07 | J31: =I31-H31 -> 0.02 | L31: =L13 -> 0.03 | N31: =L31*F31 -> 0.0021 | Q31: =Q13 -> 0.1 | S31: =Q31*F31 -> 0.007
B32: Alternatives: | C32: 0.25 | D32: =SUM(F32:F36) -> 0.18 | E32: Gold | F32: 0 | H32: 0 | I32: =F32 -> 0 | J32: =I32-H32 -> 0 | N32: =L32*F32 -> 0 | S32: =Q32*F32 -> 0
E33: Tactical | F33: 0.09 | H33: 0.03 | I33: =F33 -> 0.09 | J33: =I33-H33 -> 0.06 | L33: =L15 -> 0.02 | N33: =L33*F33 -> 0.0018 | Q33: =Q15 -> 0.02 | S33: =Q33*F33 -> 0.0018
E34: Abrax | F34: 0.05 | H34: 0.05 | I34: =F34 -> 0.05 | J34: =I34-H34 -> 0 | L34: =L16 -> 0.05 | N34: =L34*F34 -> 0.0025 | Q34: =Q16 -> 0.04 | S34: =Q34*F34 -> 0.002
E35: Syquant | F35: 0 | H35: 0 | I35: =F35 -> 0 | J35: =I35-H35 -> 0 | N35: =L35*F35 -> 0 | S35: =Q35*F35 -> 0
E36: Cimco | F36: 0.04 | H36: 0.04 | I36: =F36 -> 0.04 | J36: =I36-H36 -> 0 | L36: 0.05 | N36: =L36*F36 -> 0.002 | Q36: 0.05 | S36: =Q36*F36 -> 0.002
E37: Commodities Fund | F37: 0.04 | H37: 0 | I37: =F37 -> 0.04 | J37: =I37-H37 -> 0.04 | L37: =L17 -> 0.05 | N37: =L37*F37 -> 0.002 | Q37: =Q17 -> 0.04 | S37: =Q37*F37 -> 0.0016
B38: Cash: | C38: 1 | D38: =100%-D32-D28-D25 -> 0.18 | G38: 0.1 | H38: 0.16 | I38: =D38 -> 0.18 | J38: =I38-H38 -> 0.02 | L38: =L18 -> -0.004 | N38: =L38*D38 -> -0.00072
Q39: =Q19 -> 0.05 | S39: =Q39*G38 -> 0.005
B42: Balanced Profile | L42: 12 Mos E® | N42: =SUM(N45:N59) -> 0.03958 | Q42: =Q22 -> Risk= | S42: =SUM(S45:S59) -> 0.0926
H43: =H23 -> Q2 | I43: =I23 -> Q3 | J43: =J23 -> Delta (Q3-Q2)
B44: Statutory Max | D44: =D24 -> Q3 2016 | E44: Vector | F44: Vector Weight | G44: Active USD Long
B45: Equities: | C45: 0.7 | D45: =SUM(F45:F50) -> 0.5 | E45: Cell D | F45: 0.37 | H45: 0.42 | I45: ='[1]Q2 16'!I40 -> 0.42 | J45: =I45-H45 -> 0 | L45: =L25 -> 0.05 | N45: =L45*F45 -> 0.0185 | Q45: =Q8 -> 0.15 | S45: =Q45*F45 -> 0.0555
E46: Exclusif 21 | F46: 0.03 | H46: 0.06 | I46: ='[1]Q2 16'!I41 -> 0.06 | J46: =I46-H46 -> 0 | L46: =L27 -> 0.03 | N46: =L46*F46 -> 0.0009 | Q46: =Q9 -> 0.1 | S46: =Q46*F46 -> 0.003
E47: TFC Small Caps | F47: 0.03 | H47: 0.03 | I47: ='[1]Q2 16'!I42 -> 0.04 | J47: =I47-H47 -> 0.01 | L47: =L26 -> 0.06 | N47: =L47*F47 -> 0.0018 | Q47: =Q26 -> 0.2 | S47: =Q47*F47 -> 0.006
E48: Shanti India | F48: 0.03 | H48: 0.03 | I48: ='[1]Q2 16'!I43 -> 0.04 | J48: =I48-H48 -> 0.01 | L48: 0.06 | N48: =L48*F48 -> 0.0018 | Q48: 0.15 | S48: =Q48*F48 -> 0.0045
E49: Liontrust UK small caps | F49: 0 | H49: ='[1]Q2 16'!I42 -> 0.04 | I49: ='[1]Q2 16'!I44 -> 0.03 | J49: =I49-H49 -> -0.01 | N49: =L49*F49 -> 0 | S49: =Q49*F49 -> 0
E50: Liontrust Asian | F50: 0.04 | H50: 0.03 | I50: ='[1]Q2 16'!I45 -> 0.04 | J50: =I50-H50 -> 0.01 | L50: =7% -> 0.07 | N50: =L50*F50 -> 0.0028 | Q50: 0.15 | S50: =Q50*F50 -> 0.006
B51: Bonds: | C51: 0.5 | D51: =F51+F52 -> 0.18 | E51: Cell C | F51: 0.18 | H51: ='[1]Q2 16'!I46 -> 0.15 | I51: =F51 -> 0.18 | J51: =I51-H51 -> 0.03 | L51: =L28 -> 0.03 | N51: =L51*F51 -> 0.0054 | Q51: =Q10 -> 0.055 | S51: =Q51*F51 -> 0.0099
E52: KKR NB C L/S TBC | F52: 0 | H52: ='[1]Q2 16'!I47 -> 0 | I52: =F52 -> 0 | J52: =I52-H52 -> 0 | N52: =L52*F52 -> 0 | S52: =Q52*F52 -> 0
B53: Alternatives: | C53: 0.3 | D53: =SUM(F53:F58) -> 0.24 | E53: Abrax | F53: 0.05 | H53: ='[1]Q2 16'!I48 -> 0.05 | I53: =F53 -> 0.05 | J53: =I53-H53 -> 0 | L53: =L34 -> 0.05 | N53: =L53*F53 -> 0.0025 | Q53: =Q16 -> 0.04 | S53: =Q53*F53 -> 0.002
E54: Gold | F54: 0.03 | H54: ='[1]Q2 16'!I49 -> 0 | I54: =F54 -> 0.03 | J54: =I54-H54 -> 0.03 | N54: =L54*F54 -> 0 | S54: =Q54*F54 -> 0
E55: Tactical | F55: 0.06 | H55: ='[1]Q2 16'!I50 -> 0.04 | I55: =F55 -> 0.06 | J55: =I55-H55 -> 0.02 | L55: =L33 -> 0.02 | N55: =L55*F55 -> 0.0012 | Q55: =Q15 -> 0.02 | S55: =Q55*F55 -> 0.0012
E56: Commodities Fund | F56: 0.05 | H56: 0 | I56: =F56 -> 0.05 | J56: =I56-H56 -> 0.05 | L56: =L37 -> 0.05 | N56: =L56*F56 -> 0.0025 | Q56: =Q17 -> 0.04 | S56: =Q56*F56 -> 0.002
E57: Syquant | F57: 0 | H57: 0 | I57: =F57 -> 0 | J57: =I57-H57 -> 0 | N57: =L57*F57 -> 0 | S57: =Q57*F57 -> 0
E58: Cimco | F58: 0.05 | H58: ='[1]Q2 16'!I52 -> 0.05 | I58: =F58 -> 0.05 | J58: =I58-H58 -> 0 | L58: =L36 -> 0.05 | N58: =L58*F58 -> 0.0025 | Q58: =Q36 -> 0.05 | S58: =Q58*F58 -> 0.0025
B59: Cash: | C59: 1 | D59: =100%-D53-D51-D45 -> 0.08 | G59: 0.12 | H59: 0.05 | I59: =D59 -> 0.08 | J59: =I59-H59 -> 0.03 | L59: =L38 -> -0.004 | N59: =L59*D59 -> -0.00032
Q60: =Q39 -> 0.05 | S60: =Q60*G59 -> 0.006
